{
  "name": "Blue",
  "colors": {
    "titleBar": "0xDD0A0A2A",
    "titleText": "0xFF88AAFF",
    "closeButton": "0xFFFF5555",
    "minimizeButton": "0xFF88AAFF",
    "windowBackground": "0xBB06061A",
    "windowBorder": "0xFF203060",
    "windowBorderActive": "0xFF4477DD",
    "taskbar": "0xDD050514",
    "taskbarButton": "0xFF0A0A2A",
    "taskbarButtonActive": "0xFF203060",
    "taskbarText": "0xFF88AAFF",
    "button": "0xFF0A0A2A",
    "buttonHover": "0xFF15153A",
    "buttonPressed": "0xFF203060",
    "buttonText": "0xFFCCDDFF",
    "textFieldBg": "0xFF040410",
    "textFieldBorder": "0xFF15153A",
    "textFieldFocused": "0xFF4477DD",
    "textFieldText": "0xFFCCDDFF",
    "cursor": "0xFF88AAFF",
    "placeholder": "0xFF202050",
    "tab": "0xFF06061A",
    "tabActive": "0xFF203060",
    "tabText": "0xFF3A3A6A",
    "tabTextActive": "0xFFFFFFFF",
    "listHover": "0x334477DD",
    "listSelected": "0xFF203060",
    "listText": "0xFF99AADD",
    "listTextSelected": "0xFFFFFFFF",
    "scrollbarTrack": "0xFF06061A",
    "scrollbarThumb": "0xFF15153A",
    "scrollbarHover": "0xFF203060",
    "accent": "0xFF4477DD",
    "accentDim": "0xFF223A70",
    "textPrimary": "0xFFCCDDFF",
    "textSecondary": "0xFF3A3A6A",
    "separator": "0xFF0A0A2A",
    "screenOverlay": "0x50000010",
    "tooltipBg": "0xEE06061A",
    "tooltipBorder": "0xFF203060"
  },
  "events": {
    "connect": "0xFF55FF55",
    "disconnect": "0xFFFF5555",
    "brand": "0xFF88AAFF",
    "plugin": "0xFF4477DD",
    "world": "0xFF55FFDD",
    "gamemode": "0xFFFFFF55",
    "packet": "0xFF888888",
    "system": "0xFFFFFFFF",
    "error": "0xFFFF4444",
    "dbSync": "0xFFAA88FF"
  },
  "gradient": {
    "top": "0xBB020210",
    "bottom": "0xBB081020"
  },
  "gradients": {
    "titleBar": { "top": "0xDD1A1A50", "bottom": "0xDD060614" },
    "button": { "top": "0xFF151545", "bottom": "0xFF060618" },
    "taskbar": { "top": "0xDD0E0E30", "bottom": "0xDD030308" },
    "windowBackground": { "top": "0xBB0E0E28", "bottom": "0xBB040412" }
  }
}
